MANIFEST.in
README.rst
requirements.txt
setup.py
stdeb.cfg
docs/Makefile
docs/api.rst
docs/conf.py
docs/index.rst
docs/license.rst
docs/quickstart.rst
init/sysv/mailman-api
mailman_api.egg-info/PKG-INFO
mailman_api.egg-info/SOURCES.txt
mailman_api.egg-info/dependency_links.txt
mailman_api.egg-info/requires.txt
mailman_api.egg-info/top_level.txt
mailmanapi/__init__.py
mailmanapi/api.py
mailmanapi/members.py
mailmanapi/utils.py
mailmanapi/templates/message.tpl
scripts/mailman-api