Metadata-Version: 1.0
Name: mailman-api
Version: 0.2.9
Summary: REST API daemon to interact with Mailman 2
Home-page: http://pypi.python.org/pypi/mailman-api/
Author: Sergio Oliveira
Author-email: sergio@tracy.com.br
License: LICENSE.txt
Platform: UNKNOWN
